AudioLoader/__init__.py
AudioLoader/utils.py
AudioLoader/music/__init__.py
AudioLoader/music/amt.py
AudioLoader/music/overlapping.pkl
AudioLoader/music/utils.py
AudioLoader/music/mss/MIDI_program_map.py
AudioLoader/music/mss/__init__.py
AudioLoader/music/mss/fastmusdb.py
AudioLoader/music/mss/moisedb23_preprocessing.py
AudioLoader/music/mss/moisesdb23.py
AudioLoader/music/mss/musdbhq.py
AudioLoader/music/mss/slakh.py
AudioLoader/music/mss/utils.py
AudioLoader/speech/__init__.py
AudioLoader/speech/mls.py
AudioLoader/speech/speechcommands.py
AudioLoader/speech/timit.py
AudioLoader-0.1.4.dist-info/METADATA
AudioLoader-0.1.4.dist-info/WHEEL
AudioLoader-0.1.4.dist-info/top_level.txt
AudioLoader-0.1.4.dist-info/RECORD
