Metadata-Version: 2.1
Name: AudioLoader
Version: 0.1.4
Summary: A collection of PyTorch audio datasets for speech and music applications
Home-page: https://github.com/KinWaiCheuk/AudioLoader
Author: KinWaiCheuk
Author-email: u3500684@connect.hku.hk
License: UNKNOWN
Platform: UNKNOWN
Classifier: Programming Language :: Python :: 3
Classifier: License :: OSI Approved :: MIT License
Classifier: Operating System :: OS Independent
Requires-Python: >=3.6
